{
  "params": {
    "a0": 0.7456227720791765,
    "b": -0.33243707004727885,
    "c": 8.583483683314684e-15
  },
  "model_form": "abs_m",
  "n_calibration_prints": 2888,
  "n_gate_prints": 2448,
  "overall_mae": 6.272964119589277,
  "overall_median_abs_pct_err": 0.8768612336915642,
  "gate_median_abs_pct_err": 0.7016579860761007,
  "per_expiry": {
    "2025-12-23": {
      "n": 743,
      "n_gate": 635,
      "mae": 0.8116235329835941,
      "median_abs_pct_err": 0.13721185753080234,
      "median_abs_pct_err_gate": 0.1007523126013172,
      "signed_median_err": 0.3213176971247026,
      "bias_flag": false
    },
    "2026-03-03": {
      "n": 753,
      "n_gate": 551,
      "mae": 1.9806098118113935,
      "median_abs_pct_err": 1.8188216187555148,
      "median_abs_pct_err_gate": 1.0611376698690385,
      "signed_median_err": 1.8820416241370708,
      "bias_flag": true
    },
    "2026-03-13": {
      "n": 1088,
      "n_gate": 958,
      "mae": 3.522995363175898,
      "median_abs_pct_err": 1.0700883449848422,
      "median_abs_pct_err_gate": 0.8154157457823965,
      "signed_median_err": 3.1191379525605583,
      "bias_flag": true
    },
    "2026-05-22": {
      "n": 304,
      "n_gate": 304,
      "mae": 40.094953779400214,
      "median_abs_pct_err": 0.8912214364408192,
      "median_abs_pct_err_gate": 0.8912214364408192,
      "signed_median_err": -37.84457915470446,
      "bias_flag": true
    }
  },
  "per_m_band": {
    "|m| 0.0-0.5": {
      "n": 779,
      "mae": 3.0689236886209352,
      "median_abs_pct_err": 0.11227168783167538,
      "median_abs_pct_err_gate": 0.11227168783167538,
      "signed_median_err": 0.5425170798004273
    },
    "|m| 0.5-1.0": {
      "n": 747,
      "mae": 9.901566293626605,
      "median_abs_pct_err": 0.45615187857798356,
      "median_abs_pct_err_gate": 0.45615187857798356,
      "signed_median_err": -0.23948144151558992
    },
    "|m| 1.0-2.0": {
      "n": 865,
      "mae": 6.799798988297753,
      "median_abs_pct_err": 1.7620717628870792,
      "median_abs_pct_err_gate": 1.3822061370618772,
      "signed_median_err": 2.4247439154826496
    },
    "|m| 2.0-3.0": {
      "n": 497,
      "mae": 4.924210619157937,
      "median_abs_pct_err": 3.63714993185908,
      "median_abs_pct_err_gate": 2.0752761945897125,
      "signed_median_err": 1.5833879735947038
    }
  },
  "per_time_band": {
    "09:30\u201310:30": {
      "n": 629,
      "n_gate": 628,
      "mae": 6.471707742048205,
      "median_abs_pct_err": 0.4505634295422472,
      "median_abs_pct_err_gate": 0.44977387128845653,
      "signed_median_err": 0.38071903689997266
    },
    "10:30\u201313:00": {
      "n": 1373,
      "n_gate": 1204,
      "mae": 5.918308034122245,
      "median_abs_pct_err": 0.8755682866522886,
      "median_abs_pct_err_gate": 0.8018239773798868,
      "signed_median_err": 1.700996428203057
    },
    "13:00\u201315:00": {
      "n": 764,
      "n_gate": 516,
      "mae": 6.885510738173791,
      "median_abs_pct_err": 1.5623542780603905,
      "median_abs_pct_err_gate": 0.9053558948100454,
      "signed_median_err": 1.009083841647779
    },
    "15:00\u201316:00": {
      "n": 122,
      "n_gate": 100,
      "mae": 5.403680924679451,
      "median_abs_pct_err": 0.9182734467300998,
      "median_abs_pct_err_gate": 0.17090318037440966,
      "signed_median_err": 0.5061836023350226
    }
  },
  "biased_days": [
    "2026-03-03",
    "2026-03-13",
    "2026-05-22"
  ],
  "warning_unreliable": true
}